vbox_operator/__init__.py
vbox_operator/__main__.py
vbox_operator/commands_dict.py
vbox_operator/menu.py
vbox_operator/operations.py
vbox_operator-0.0.4.dist-info/LICENSE
vbox_operator-0.0.4.dist-info/METADATA
vbox_operator-0.0.4.dist-info/WHEEL
vbox_operator-0.0.4.dist-info/entry_points.txt
vbox_operator-0.0.4.dist-info/top_level.txt
vbox_operator-0.0.4.dist-info/RECORD
