Metadata-Version: 2.1
Name: vbox-operator
Version: 0.0.4
Summary: An interactive command line interface for VirtualBox.
Home-page: https://github.com/Humoud/vbox-operator
Author: Humoud Al Saleh
Author-email: humoud@corpse.io
License: UNKNOWN
Project-URL: Bug Tracker, https://github.com/Humoud/vbox-operator/issues
Keywords: virtualbox vbox operator
Platform: UNKNOWN
Classifier: License :: OSI Approved :: MIT License
Classifier: Operating System :: OS Independent
Classifier: Programming Language :: Python :: 3
Classifier: Programming Language :: Python :: 3.6
Classifier: Programming Language :: Python :: 3.7
Classifier: Programming Language :: Python :: 3.8
Classifier: Programming Language :: Python :: 3.9
Classifier: Programming Language :: Python :: 3 :: Only
Requires-Python: >=3.6
Requires-Dist: prompt-toolkit
Requires-Dist: Pygments
